{
    "title":"Engineering",
    "data":{
        "Problem":187,
        "Auto":166,
        "Attention to detail":107,
        "Project management":84,
        "D proficiency":68,
        "Technical knowledge":65,
        "D modeling":60,
        "Environmental impact assessment":58,
        "Troubleshooting":52,
        "Environmental regulations":49,
        "Six":48,
        "Quality control":46,
        "Energy efficiency":44,
        "Client communication":43,
        "C A D software":40,
        "Data analysis":38,
        "Electrical engineering":37,
        "Zoning regulations":36,
        "Communication skills":35,
        "Environmental impact assessments":35
    }
}